meze/__init__.py
meze/apps.py
meze/decorators.py
meze/response.py
meze/telepath.py
meze/views.py
meze/static/meze/fonts/.gitignore
meze/static/meze/images/.gitignore
meze/static/meze/js/.gitignore
meze/templates/meze/bootstrap.html
meze/test/__init__.py
meze/test/apps.py
meze/test/settings.py
meze/test/urls.py
meze/test/tests/__init__.py
meze/ui/__init__.py
meze/ui/forms.py
meze-0.1a11.dist-info/METADATA
meze-0.1a11.dist-info/WHEEL
meze-0.1a11.dist-info/top_level.txt
meze-0.1a11.dist-info/RECORD
